holden-0.1.9.dist-info/METADATA
holden-0.1.9.dist-info/WHEEL
holden-0.1.9.dist-info/entry_points.txt
holden-0.1.9.dist-info/licenses/LICENSE
holden/__init__.py
holden/applications.py
holden/base.py
holden/check.py
holden/composites.py
holden/export.py
holden/graphs.py
holden/options.py
holden/report.py
holden/traits.py
holden/traverse.py
holden/utilities.py
holden/workshop.py
holden-0.1.9.dist-info/RECORD
