Metadata-Version: 2.1
Name: holden
Version: 0.1.9
Summary: Lightweight, easy-to-use, flexible composite data structures
Author-Email: Corey Rayburn Yung <coreyrayburnyung@gmail.com>
License: Apache Software License 2.0
Classifier: Development Status :: 4 - Beta
Classifier: Environment :: Console
Classifier: Intended Audience :: Developers
Classifier: Intended Audience :: Education
Classifier: License :: OSI Approved :: Apache Software License
Classifier: Programming Language :: Python
Classifier: Programming Language :: Python :: 3
Classifier: Programming Language :: Python :: 3 :: Only
Classifier: Programming Language :: Python :: 3.11
Classifier: Programming Language :: Python :: 3.12
Classifier: Programming Language :: Python :: 3.13
Classifier: Topic :: Software Development
Project-URL: Documentation, https://WithPrecedent.github.io/holden
Project-URL: Repository, https://github.com/WithPrecedent/holden
Project-URL: Issues, https://github.com/WithPrecedent/holden/issues
Project-URL: Changelog, https://WithPrecedent.github.io/holden/changelog
Requires-Python: >=3.11
Requires-Dist: bunches
Requires-Dist: wonka
